pytmv1/__about__.py
pytmv1/__init__.py
pytmv1/adapter.py
pytmv1/client.py
pytmv1/core.py
pytmv1/exception.py
pytmv1/mapper.py
pytmv1/py.typed
pytmv1/result.py
pytmv1/utils.py
pytmv1/api/__init__.py
pytmv1/api/account.py
pytmv1/api/alert.py
pytmv1/api/api_key.py
pytmv1/api/email.py
pytmv1/api/endpoint.py
pytmv1/api/note.py
pytmv1/api/oat.py
pytmv1/api/object.py
pytmv1/api/sandbox.py
pytmv1/api/script.py
pytmv1/api/system.py
pytmv1/api/task.py
pytmv1/model/__init__.py
pytmv1/model/common.py
pytmv1/model/enum.py
pytmv1/model/request.py
pytmv1/model/response.py
pytmv1-0.9.3.dist-info/METADATA
pytmv1-0.9.3.dist-info/WHEEL
pytmv1-0.9.3.dist-info/licenses/LICENSE
pytmv1-0.9.3.dist-info/RECORD
