Metadata-Version: 2.4
Name: pytmv1
Version: 0.9.3
Summary: Python library for Trend Micro Vision One
Project-URL: Source, https://github.com/TrendATI/pytmv1
Project-URL: Issues, https://github.com/TrendATI/pytmv1/issues
Author-email: Thomas Legros <thomas_legros@trendmicro.com>
Maintainer-email: TrendATI <ati-integration@trendmicro.com>
License-Expression: Apache-2.0
License-File: LICENSE
Classifier: Development Status :: 2 - Pre-Alpha
Classifier: Intended Audience :: Developers
Classifier: License :: OSI Approved :: Apache Software License
Classifier: Natural Language :: English
Classifier: Operating System :: OS Independent
Classifier: Programming Language :: Python :: 3.8
Classifier: Programming Language :: Python :: 3.9
Classifier: Programming Language :: Python :: 3.10
Classifier: Programming Language :: Python :: 3.11
Classifier: Topic :: Internet :: WWW/HTTP
Classifier: Topic :: Software Development :: Libraries
Requires-Python: >=3.8
Requires-Dist: beautifulsoup4~=4.11.1
Requires-Dist: pydantic~=2.5.3
Requires-Dist: requests~=2.32.3
Provides-Extra: dev
Requires-Dist: hatch~=1.6.3; extra == 'dev'
Requires-Dist: psutil~=5.9.4; extra == 'dev'
Requires-Dist: pytest-cov~=4.0.0; extra == 'dev'
Requires-Dist: pytest-mock~=3.10.0; extra == 'dev'
Requires-Dist: pytest~=7.2.0; extra == 'dev'
